CHANGELOG.txt
MANIFEST.in
README.txt
setup.py
basic_card/__init__.py
basic_card_hannu_hell.egg-info/PKG-INFO
basic_card_hannu_hell.egg-info/SOURCES.txt
basic_card_hannu_hell.egg-info/dependency_links.txt
basic_card_hannu_hell.egg-info/top_level.txt