Metadata-Version: 2.1
Name: basic-card-hannu-hell
Version: 0.0.1
Summary: Basic card game functions
Home-page: https://github.com/hannu-hell/basic_card
Author: Hanoon Malik
Author-email: hannu_hell@hotmail.com
License: UNKNOWN
Platform: UNKNOWN
Classifier: Programming Language :: Python :: 3
Classifier: License :: OSI Approved :: MIT License
Classifier: Operating System :: OS Independent
Requires-Python: >=3.6
